mercury_orm-0.6.3.dist-info/licenses/LICENSE
mercuryorm/__init__.py
mercuryorm/base.py
mercuryorm/exceptions.py
mercuryorm/fields.py
mercuryorm/file.py
mercuryorm/managers.py
mercuryorm/record_manager.py
mercuryorm/zendesk_manager.py
mercuryorm/client/__init__.py
mercuryorm/client/connection.py
tests/__init__.py
tests/conftest.py
tests/test_attachment_field.py
tests/test_base.py
tests/test_client_connection.py
tests/test_managers.py
tests/test_record_manager.py
tests/test_zendesk_manager.py
mercury_orm-0.6.3.dist-info/METADATA
mercury_orm-0.6.3.dist-info/WHEEL
mercury_orm-0.6.3.dist-info/top_level.txt
mercury_orm-0.6.3.dist-info/RECORD
