Metadata-Version: 2.4
Name: mercury-orm
Version: 0.6.3
Summary: ORM for Custom Objects de Zendesk
Home-page: https://github.com/BCR-CX/mercury-orm
Author: Pedro Andrade
Author-email: pedro.moisesandrade@gmail.com
License: MIT
Project-URL: Homepage, https://github.com/BCR-CX/mercury-orm
Project-URL: Issues, https://github.com/BCR-CX/mercury-orm/issues
Classifier: Programming Language :: Python :: 3
Classifier: License :: OSI Approved :: MIT License
Classifier: Operating System :: OS Independent
Requires-Python: >=3.8
License-File: LICENSE
Requires-Dist: requests>=2.31.0
Requires-Dist: python-dotenv>=1.0.0
Requires-Dist: Unidecode==1.3.8
Dynamic: author
Dynamic: author-email
Dynamic: classifier
Dynamic: description
Dynamic: description-content-type
Dynamic: home-page
Dynamic: license
Dynamic: license-file
Dynamic: project-url
Dynamic: requires-dist
Dynamic: requires-python
Dynamic: summary
